pycid_dev/__init__.py
pycid_dev/client.py
pycid_dev/lib/__init__.py
pycid_dev/lib/attribute/__init__.py
pycid_dev/lib/attribute/attribute.py
pycid_dev/lib/attribute/constants.py
pycid_dev/lib/authentication/__init__.py
pycid_dev/lib/authentication/__main__.py
pycid_dev/lib/authentication/authentication.py
pycid_dev/lib/authentication/refresh.py
pycid_dev/lib/component/__init__.py
pycid_dev/lib/component/component.py
pycid_dev/lib/craft/__init__.py
pycid_dev/lib/craft/craft.py
pycid_dev/lib/crate/__init__.py
pycid_dev/lib/crate/crate.py
pycid_dev/lib/tree/__init__.py
pycid_dev/lib/tree/tree.py
pycid_dev-0.0.38.dist-info/LICENSE
pycid_dev-0.0.38.dist-info/METADATA
pycid_dev-0.0.38.dist-info/WHEEL
pycid_dev-0.0.38.dist-info/top_level.txt
pycid_dev-0.0.38.dist-info/RECORD
