Metadata-Version: 2.2
Name: pycid-dev
Version: 0.0.38
Summary: WIP API for CID
Requires-Python: >=3.6
License-File: LICENSE
Requires-Dist: requests>=2.28.2
Requires-Dist: fasteners
Requires-Dist: loguru
